classInfo.py
classInfo-1.0.1.dist-info/METADATA
classInfo-1.0.1.dist-info/WHEEL
classInfo-1.0.1.dist-info/top_level.txt
classInfo-1.0.1.dist-info/RECORD
