Metadata-Version: 2.1
Name: classInfo
Version: 1.0.1
Summary: classInfo is useful to write information about everything(almost)
Home-page: https://github.com/IM-code111/jsonbase-1.0.0
Author: WinXpDev
Author-email: muhammad184276@gmail.com
License: UNKNOWN
Platform: UNKNOWN
Classifier: Programming Language :: Python :: 3
Classifier: License :: OSI Approved :: MIT License
Classifier: Operating System :: OS Independent
Requires-Python: >=3.6
